llama_index/callbacks/arize_phoenix/__init__.py
llama_index/callbacks/arize_phoenix/base.py
flying_delta_callbacks_arize_phoenix-0.0.1.dist-info/METADATA
flying_delta_callbacks_arize_phoenix-0.0.1.dist-info/WHEEL
flying_delta_callbacks_arize_phoenix-0.0.1.dist-info/RECORD
